Metadata-Version: 1.1
Name: yqmq
Version: 0.0.5
Summary: YQMQ Python AMQP Client Library With Gevent Support
Home-page: https://github.com/cainbit/yqmq
Author: Wu Wenchao
Author-email: cainbit@gmail.com
License: MIT
Keywords: amqp,gevent,rabbitmq
Platform: UNKNOWN
Classifier: Development Status :: 2 - Pre-Alpha
Classifier: Intended Audience :: Developers
Classifier: License :: OSI Approved :: MIT License
Classifier: Natural Language :: English
Classifier: Operating System :: OS Independent
Classifier: Programming Language :: Python :: 2.7
Classifier: Topic :: Communications
Classifier: Topic :: Internet
Classifier: Topic :: Software Development :: Libraries
Classifier: Topic :: Software Development :: Libraries :: Python Modules
Classifier: Topic :: System :: Networking
